{
  "game_mode": "tournament",
  "table_size": 4,
  "starting_chips": 2000,
  "small_blind": 10,
  "big_blind": 20,
  "hands_per_level": 8,
  "tournament_levels": [
    {"small": 10, "big": 20, "ante": 0},
    {"small": 15, "big": 30, "ante": 0},
    {"small": 25, "big": 50, "ante": 0},
    {"small": 40, "big": 80, "ante": 80},
    {"small": 60, "big": 120, "ante": 120},
    {"small": 100, "big": 200, "ante": 200},
    {"small": 150, "big": 300, "ante": 300},
    {"small": 250, "big": 500, "ante": 500}
  ],
  "variety_rotation_enabled": true,
  "variety_rotation_interval_hands": 24,
  "variety_segments": [
    {
      "id": "championship_sng",
      "title": "Championship Sit & Go",
      "mode": "tournament",
      "duration_hands": 24,
      "tempo": "standard",
      "table_skin": "championship",
      "accent": "#e6b94a",
      "viewer_explainer": "A classic sit-and-go: rising blinds, no rebuys, trophy finish.",
      "strategy_hint": "Use balanced stack-aware tournament poker.",
      "hands_per_level": 8
    },
    {
      "id": "turbo_sng",
      "title": "Turbo Pressure Sit & Go",
      "mode": "tournament",
      "duration_hands": 18,
      "tempo": "turbo",
      "table_skin": "turbo",
      "accent": "#ff7b4a",
      "viewer_explainer": "A shorter-blind sit-and-go where stacks get pressured quickly.",
      "strategy_hint": "Blinds rise quickly; favor position and decisive fold-equity spots.",
      "hands_per_level": 4
    },
    {
      "id": "ante_splash_cash",
      "title": "Ante Splash Cash",
      "mode": "cash",
      "duration_hands": 18,
      "tempo": "splash",
      "table_skin": "splash",
      "accent": "#5ed39a",
      "viewer_explainer": "Everyone antes, so more hands begin with something worth fighting for.",
      "strategy_hint": "Antes improve steal prices and pot odds; defend wider in good spots.",
      "small_blind": 10,
      "big_blind": 20,
      "ante": 5,
      "starting_chips": 2500
    }
  ],
  "player_profiles": [
    {"id": "atlas", "name": "Atlas", "persona": "disciplined tight-aggressive analyst", "model": "auto", "color": "#e7bd55", "voice": "", "temperature": 0.18},
    {"id": "vega", "name": "Vega", "persona": "fearless loose-aggressive pressure player", "model": "auto", "color": "#ef6b67", "voice": "", "temperature": 0.38},
    {"id": "nova", "name": "Nova", "persona": "balanced adaptive opponent reader", "model": "auto", "color": "#61b7ff", "voice": "", "temperature": 0.27},
    {"id": "echo", "name": "Echo", "persona": "patient deceptive trap-oriented player", "model": "auto", "color": "#a98aff", "voice": "", "temperature": 0.3}
  ],
  "rng_seed": null,
  "action_delay_ms": 1250,
  "deal_delay_ms": 320,
  "stage_delay_ms": 4500,
  "between_hands_delay_ms": 6500,
  "between_tournaments_delay_ms": 15000,
  "animation_duration_ms": 720,
  "continuous_play": true,
  "start_paused": false,
  "allow_multiple_instances": false,
  "single_instance_lock_path": "data/aipoker.pid",
  "fullscreen": true,
  "reduced_motion": false,
  "classic_two_color_cards": true,
  "analysis_depth": "full",
  "equity_samples": 1600,
  "overlay_enabled": true,
  "overlay_host": "127.0.0.1",
  "overlay_port": 8765,
  "overlay_background": "#071c13",
  "overlay_accent": "#e6b94a",
  "overlay_font": "Inter, Segoe UI, Arial, sans-serif",
  "overlay_layout": "horizontal",
  "overlay_audio_enabled": true,
  "overlay_disclaimer_enabled": true,
  "overlay_director_enabled": true,
  "overlay_rotation_enabled": true,
  "overlay_rotation_interval_ms": 9000,
  "overlay_narration_enabled": false,
  "overlay_recap_duration_ms": 7500,
  "overlay_moment_duration_ms": 6200,
  "overlay_visual_debug": false,
  "overlay_engagement_enabled": true,
  "overlay_follow_message": "Follow for 24/7 autonomous AI poker.",
  "overlay_chat_prompt": "Call out the next winner in chat.",
  "casino_bumpers_enabled": true,
  "casino_bumper_frequency": "selected_hands",
  "casino_bumper_duration_ms": 6500,
  "casino_bumper_responsible_label": true,
  "audio_enabled": true,
  "audio_volume": 0.45,
  "ambience_enabled": true,
  "ambience_volume": 0.16,
  "effects_volume": 0.72,
  "music_enabled": true,
  "music_path": "music",
  "music_volume": 0.18,
  "music_shuffle": true,
  "sound_effects_path": "sound_effects",
  "voice_volume": 0.8,
  "audio_cache_path": "data/audio_cache",
  "tts_enabled": false,
  "tts_volume": 0.8,
  "tts_rate": 175,
  "tts_voice": "",
  "stats_path": "data/leaderboard.json",
  "checkpoint_path": "data/checkpoint.json",
  "hand_history_path": "data/hand_history.jsonl"
}
